boml/__init__.py
boml/extension.py
boml/utils.py
boml/boml_optimizer/__init__.py
boml/boml_optimizer/optimizer.py
boml/load_data/__init__.py
boml/load_data/em_utils.py
boml/load_data/experiment.py
boml/load_data/datasets/__init__.py
boml/load_data/datasets/dl_utils.py
boml/load_data/datasets/load.py
boml/load_data/datasets/load_full_dataset.py
boml/load_data/datasets/structures.py
boml/load_data/datasets/tiff2tensor.py
boml/lower_iter/__init__.py
boml/lower_iter/aggr.py
boml/lower_iter/inner_grad.py
boml/lower_iter/simple.py
boml/optimizer/__init__.py
boml/optimizer/adam.py
boml/optimizer/momentum.py
boml/optimizer/opt.py
boml/optimizer/sgd.py
boml/setup_model/__init__.py
boml/setup_model/feedforward.py
boml/setup_model/meta_init_v1.py
boml/setup_model/meta_init_v2.py
boml/setup_model/meta_repr_v1.py
boml/setup_model/meta_repr_v2.py
boml/setup_model/network.py
boml/setup_model/network_utils.py
boml/upper_iter/__init__.py
boml/upper_iter/darts.py
boml/upper_iter/implicit.py
boml/upper_iter/outer_grad.py
boml/upper_iter/reverse.py
boml/upper_iter/simple.py
BOML-0.1.2.dist-info/LICENSE
BOML-0.1.2.dist-info/METADATA
BOML-0.1.2.dist-info/WHEEL
BOML-0.1.2.dist-info/top_level.txt
BOML-0.1.2.dist-info/RECORD
